pydec/__init__.py
pydec/_composition.py
pydec/_composition_str.py
pydec/exception_utils.py
pydec/overrides.py
pydec/utils.py
pydec/variable_functions.py
pydec/core/__init__.py
pydec/core/decBLAS/__init__.py
pydec/core/decBLAS/ops.py
pydec/core/decMVF/__init__.py
pydec/core/decMVF/ops.py
pydec/core/decMVF/shapley.py
pydec/core/decOVF/__init__.py
pydec/core/decOVF/algorithms.py
pydec/core/decOVF/ops.py
pydec/core/decOVF/states.py
pydec/nn/__init__.py
pydec/nn/functional.py
pydec/nn/modules/__init__.py
pydec/nn/modules/activation.py
pydec/nn/modules/container.py
pydec/nn/modules/linear.py
pydec/nn/modules/meta.py
pydec/nn/modules/module.py
pydec/nn/utils/__init__.py
pydec/nn/utils/rnn.py
test/__init__.py
test/_composition_test.py
test/decomposition_test.py
test/variable_functions_test.py
pydec-0.3.0.dist-info/LICENSE
pydec-0.3.0.dist-info/METADATA
pydec-0.3.0.dist-info/WHEEL
pydec-0.3.0.dist-info/top_level.txt
pydec-0.3.0.dist-info/RECORD
