Metadata-Version: 2.1
Name: pydec
Version: 0.3.0
Summary: Linear decomposition toolkit for neural network based on pytorch.
Home-page: https://github.com/DoubleVII/pydec/
Author: Sen Yang
Author-email: yangsen@smail.nju.edu.cn
License: MIT
Classifier: License :: OSI Approved :: MIT License
Classifier: Programming Language :: Python
Classifier: Programming Language :: Python :: 3
Classifier: Programming Language :: Python :: 3.9
Classifier: Programming Language :: Python :: Implementation :: CPython
Classifier: Programming Language :: Python :: Implementation :: PyPy
Requires-Python: >=3.7.0
License-File: LICENSE
Requires-Dist: torch (>=1.11.0)
Requires-Dist: numpy
